Metadata-Version: 2.1
Name: localstack-persistence-plugin
Version: 0.1.0.dev1
Summary: plugin containing persistence code
Home-page: https://github.com/localstack/localstack-persistence-plugin
Author: LocalStack Contributors
Author-email: info@localstack.cloud
Requires-Dist: localstack (>=1.4.1.dev)
Requires-Dist: moto-ext
Provides-Extra: dev
Requires-Dist: black (>=22.1) ; extra == 'dev'
Requires-Dist: isort (>=5.10) ; extra == 'dev'
Requires-Dist: pytest (>=7.0) ; extra == 'dev'
Requires-Dist: plux (>=1.3.1) ; extra == 'dev'
Requires-Dist: localstack[runtime] (>=1.4.1.dev) ; extra == 'dev'
Requires-Dist: coverage[toml] (>=5.0.0) ; extra == 'dev'
Requires-Dist: python-minifier (>=2.8.0) ; extra == 'dev'
